TP_sendNotify/__init__.py
TP_sendNotify-2024.9.1.dist-info/LICENSE
TP_sendNotify-2024.9.1.dist-info/METADATA
TP_sendNotify-2024.9.1.dist-info/WHEEL
TP_sendNotify-2024.9.1.dist-info/top_level.txt
TP_sendNotify-2024.9.1.dist-info/RECORD
