Metadata-Version: 2.1
Name: TP-sendNotify
Version: 2024.9.1
Summary: Sending message notification to Discord, Telegram, Slack
Home-page: https://github.com/truocphan/TP-sendNotify
Author: TP Cyber Security
Author-email: tpcybersec2023@gmail.com
License: MIT
Keywords: TPCyberSec
Platform: UNKNOWN
Classifier: Programming Language :: Python :: 3
Classifier: Programming Language :: Python :: 2
Classifier: Programming Language :: Python :: Implementation :: Jython
Requires-Dist: certifi
Requires-Dist: charset-normalizer
Requires-Dist: idna
Requires-Dist: json-duplicate-keys
Requires-Dist: requests
Requires-Dist: urllib3
